devautomator/__init__.py
devautomator-0.1.0.dist-info/licenses/LICENSE
devautomator-0.1.0.dist-info/METADATA
devautomator-0.1.0.dist-info/WHEEL
devautomator-0.1.0.dist-info/entry_points.txt
devautomator-0.1.0.dist-info/top_level.txt
devautomator-0.1.0.dist-info/RECORD
